test_proj_1560/TestMod1.py
test_proj_1560/__init__.py
test_proj_1560/items.txt
test_proj_1560/test_proj_1560.py
test_proj_1560-0.1.5.dist-info/METADATA
test_proj_1560-0.1.5.dist-info/WHEEL
test_proj_1560-0.1.5.dist-info/licenses/LICENSE
test_proj_1560-0.1.5.dist-info/RECORD
